envy/__init__.py
envy/__main__.py
envy/envy.py
envy/lib/__init__.py
envy/lib/file_downloader.py
envy/lib/config/__init__.py
envy/lib/config/envy_config.py
envy/lib/config/file.py
envy/lib/config/schema.py
envy/lib/docker_manager/__init__.py
envy/lib/docker_manager/compose_manager.py
envy/lib/docker_manager/connection_tester.py
envy/lib/docker_manager/container_manager.py
envy/lib/docker_manager/docker_manager.py
envy/lib/docker_manager/image_manager.py
envy/lib/docker_manager/image_creators/__init__.py
envy/lib/docker_manager/image_creators/apt_image_creator.py
envy/lib/docker_manager/image_creators/image_creator.py
envy/lib/io/__init__.py
envy/lib/io/step_printer.py
envy/lib/setup_step/__init__.py
envy/lib/setup_step/apt_package_manager_step.py
envy/lib/setup_step/assignable_trigger_step.py
envy/lib/setup_step/builder.py
envy/lib/setup_step/package_manager_step.py
envy/lib/setup_step/remote_setup_step.py
envy/lib/setup_step/script_setup_step.py
envy/lib/setup_step/setup_step.py
envy/lib/state/__init__.py
envy/lib/state/directory.py
envy/lib/state/envy_state.py
envy/lib/triggers/__init__.py
envy/lib/triggers/trigger.py
envy/lib/triggers/trigger_always.py
envy/lib/triggers/trigger_group.py
envy/lib/triggers/trigger_per_container.py
envy/lib/triggers/trigger_step.py
envy/lib/triggers/trigger_system_package.py
envy/lib/triggers/trigger_watchfile.py
envy_project-2.0.0.dist-info/LICENSE
envy_project-2.0.0.dist-info/METADATA
envy_project-2.0.0.dist-info/WHEEL
envy_project-2.0.0.dist-info/entry_points.txt
envy_project-2.0.0.dist-info/top_level.txt
envy_project-2.0.0.dist-info/RECORD
