Metadata-Version: 2.1
Name: envy-project
Version: 2.0.0
Summary: Create and manage developments environment.
Home-page: https://github.com/envy-project/envy
Author: Envy Team
Author-email: alex@magmastone.net
License: MIT
Platform: UNKNOWN
Classifier: License :: OSI Approved :: MIT License
Classifier: Programming Language :: Python
Classifier: Programming Language :: Python :: 3
Classifier: Programming Language :: Python :: 3.7
Classifier: Programming Language :: Python :: Implementation :: CPython
Classifier: Programming Language :: Python :: Implementation :: PyPy
Requires-Python: >=3.7.0
Requires-Dist: docker
Requires-Dist: schema
Requires-Dist: envy-project-dockerpty-republish
Requires-Dist: pyyaml
Requires-Dist: requests
